django_streams/__init__.py
django_streams/apps.py
django_streams/engine.py
django_streams/factories.py
django_streams/management/commands/__init__.py
django_streams/management/commands/worker.py
django_streams/test_utils/__init__.py
django_streams/test_utils/test_client.py
django_streams-3.0.0.dist-info/LICENSE
django_streams-3.0.0.dist-info/METADATA
django_streams-3.0.0.dist-info/WHEEL
django_streams-3.0.0.dist-info/RECORD
