Metadata-Version: 2.1
Name: django-streams
Version: 3.0.0
Summary: Django application to produce/consume events from Kafka
Author: Marcos Schroh
Author-email: marcos.schroh@kpn.com
Requires-Python: >=3.9,<4.0
Classifier: Framework :: AsyncIO
Classifier: Intended Audience :: Developers
Classifier: Programming Language :: Python :: 3
Classifier: Programming Language :: Python :: 3.9
Classifier: Programming Language :: Python :: 3.10
Classifier: Programming Language :: Python :: 3.11
Classifier: Programming Language :: Python :: 3.12
Classifier: Programming Language :: Python :: 3 :: Only
Classifier: Topic :: Software Development :: Libraries :: Application Frameworks
Classifier: Topic :: System :: Distributed Computing
Classifier: Topic :: System :: Networking
Requires-Dist: django (>=2)
Requires-Dist: kstreams (>=0.23.0,<0.27.0)
